<?xml version="1.0" encoding="ks_c_5601_1987" ?>
<CHARACTER>
    <COMMAND_LIST>
        <COMMAND NAME="KARA_COMB_NUNCHAKU" LOOP="0" TOTALTIME="0.570000">
            <ACTIONEVENT CLASSNAME="CActionEvent_ActionAni" EVENTNAME="Kara_Obj_Nunchaku" TYPENAME="ActionAnimation" ANIMATIONNAME="Kara_Obj_Nunchaku" FADEIN="0.100000" FADEOUT="0.100000" WEIGHT="1.000000" EVENTTIME="0.000000" EVENTENDTIME="0.000000" />
        </COMMAND>
        <COMMAND NAME="TAMA_KKP" LOOP="0" TOTALTIME="0.970000">
            <ACTIONEVENT CLASSNAME="CActionEvent_ActionAni" EVENTNAME="TAMA_KKP" TYPENAME="ActionAnimation" ANIMATIONNAME="TAMA_KKP" FADEIN="0.100000" FADEOUT="0.100000" WEIGHT="1.000000" EVENTTIME="0.000000" EVENTENDTIME="0.000000" />
        </COMMAND>
        <COMMAND NAME="TAMA_PKK" LOOP="0" TOTALTIME="0.970000">
            <ACTIONEVENT CLASSNAME="CActionEvent_ActionAni" EVENTNAME="TAMA_PKK" TYPENAME="ActionAnimation" ANIMATIONNAME="TAMA_PKK" FADEIN="0.100000" FADEOUT="0.100000" WEIGHT="1.000000" EVENTTIME="0.000000" EVENTENDTIME="0.000000" />
        </COMMAND>
    </COMMAND_LIST>
</CHARACTER>
