<?xml version="1.0" encoding="ks_c_5601_1987" ?>
<GAMEENTITY>
    <MODEL_RES_LIST COUNT="1">
        <PROPERTYBAG NAME="Stage_Effect_Entity" FILENAME="Stage_Effect_Entity.xml" COMMENT="" />
    </MODEL_RES_LIST>
    <ANIM_RES_LIST COUNT="0" VSNAME="" />
    <SOUND_RES_LIST COUNT="0" />
    <EFFECT_RES_LIST COUNT="1">
        <PROPERTYBAG NAME="Orion_Stage_Run" FILENAME="Orion_Stage_Run.xml" COMMENT="" />
    </EFFECT_RES_LIST>
    <PARTICLE_RES_LIST COUNT="0" />
    <EXTENTITY_RES_LIST COUNT="0" />
    <COMMANDS FILENAME="Colosseum_EFFECT_ARROW_COMMANDS.XML" />
</GAMEENTITY>
