<?xml version="1.0" encoding="ks_c_5601_1987" ?>
<CHARACTER>
    <COMMAND_LIST>
        <COMMAND NAME="TR_PTERA_COMBAT_WAIT" LOOP="0" TOTALTIME="10.000000">
            <ACTIONEVENT CLASSNAME="CActionEvent_LoopAni" EVENTNAME="TR_GODZILLA_COMBAT_WAIT" TYPENAME="LoopAnimation" ANIMATIONNAME="TR_GODZILLA_COMBAT_WAIT" WEIGHT="1.000000" DELAY="0.100000" EVENTTIME="0.000000" EVENTENDTIME="0.000000" />
            <ACTIONEVENT CLASSNAME="CActionEvent_Model" EVENTNAME="EYE09" TYPENAME="Model" MODELNAME="EYE09" SHOW="1" NORESHOW="0" EVENTTIME="0.000000" EVENTENDTIME="0.000000" />
            <ACTIONEVENT CLASSNAME="CActionEvent_Model" EVENTNAME="HEAD09" TYPENAME="Model" MODELNAME="HEAD09" SHOW="1" NORESHOW="0" EVENTTIME="0.000000" EVENTENDTIME="0.000000" />
        </COMMAND>
        <COMMAND NAME="TR_PTERA_COMB_DA_K" LOOP="0" TOTALTIME="0.600000">
            <ACTIONEVENT CLASSNAME="CActionEvent_ActionAni" EVENTNAME="TR_GODZILLA_COMB_DA_K" TYPENAME="ActionAnimation" ANIMATIONNAME="TR_GODZILLA_COMB_DA_K" FADEIN="0.100000" FADEOUT="0.100000" WEIGHT="1.000000" EVENTTIME="0.000000" EVENTENDTIME="0.000000" />
            <ACTIONEVENT CLASSNAME="CActionEvent_AttackTiming" EVENTNAME="ATK_TIMING" TYPENAME="AtkTiming" EVENTTIME="0.240000" EVENTENDTIME="0.430000" ATK_POINT="10.000000" ATK_DIST="170.000000" ATK_RANGE="20.000000" IS_LAST_ATK="1" USEFANROUTINE="0" ATKRANGEBOX_MINX="-160.000000" ATKRANGEBOX_MINY="-140.000000" ATKRANGEBOX_MINZ="-600.000000" ATKRANGEBOX_MAXX="160.000000" ATKRANGEBOX_MAXY="320.000000" ATKRANGEBOX_MAXZ="-70.000000" TYPENUM="252800005" IS_WIDE_ATK="0" STUNTIME="0.000000" STATENAME="" />
            <ACTIONEVENT CLASSNAME="CActionEvent_Effect" EVENTNAME="Gozilla_Com_DP_E00" TYPENAME="Effect" EFFECTNAME="Gozilla_Com_DP_E00" OFFSETX="0.000000" OFFSETY="0.000000" OFFSETZ="0.000000" BILLX="0" BILLY="0" BILLZ="1" BILLBOARDX="1" BILLBOARDY="0" BILLBOARDALL="0" LOOP="0" BONENAME="" NEVERSTOP="0" TERMINATE="0" ALPHAGROUP="7" GRANDPARENT="0" EVENTTIME="0.000000" EVENTENDTIME="0.000000" />
            <ACTIONEVENT CLASSNAME="CActionEvent_LoopAni" EVENTNAME="TR_GODZILLA_COMBAT_WAIT" TYPENAME="LoopAnimation" ANIMATIONNAME="TR_GODZILLA_COMBAT_WAIT" WEIGHT="1.000000" DELAY="0.100000" EVENTTIME="0.000000" EVENTENDTIME="0.000000" />
            <ACTIONEVENT CLASSNAME="CActionEvent_Model" EVENTNAME="EYE04" TYPENAME="Model" MODELNAME="EYE04" SHOW="1" NORESHOW="0" EVENTTIME="0.000000" EVENTENDTIME="0.000000" />
            <ACTIONEVENT CLASSNAME="CActionEvent_Model" EVENTNAME="HEAD04" TYPENAME="Model" MODELNAME="HEAD04" SHOW="1" NORESHOW="0" EVENTTIME="0.000000" EVENTENDTIME="0.000000" />
            <ACTIONEVENT CLASSNAME="CActionEvent_Move" EVENTNAME="MOVE" TYPENAME="Movement" LENGTH="150.000000" SPEED="15.000000" ACCEL="0.000000" INVERSE="0" MOVEPLUS="0" CHARDIRPLUS="0" IGNORECOLLISION="0" EVENTTIME="0.150000" EVENTENDTIME="0.000000" />
            <ACTIONEVENT CLASSNAME="CActionEvent_Sound" EVENTNAME="TR_GODZILLA_COMB_DA_P_1" TYPENAME="Sound" SOUNDNAME="TR_GODZILLA_COMB_DA_P_1" VOLUME="255" LOOP="0" EVENTTIME="0.000000" EVENTENDTIME="0.000000" />
        </COMMAND>
        <COMMAND NAME="TR_PTERA_COMB_DA_P" LOOP="0" TOTALTIME="0.600000">
            <ACTIONEVENT CLASSNAME="CActionEvent_ActionAni" EVENTNAME="TR_GODZILLA_COMB_DA_P" TYPENAME="ActionAnimation" ANIMATIONNAME="TR_GODZILLA_COMB_DA_P" FADEIN="0.100000" FADEOUT="0.100000" WEIGHT="1.000000" EVENTTIME="0.000000" EVENTENDTIME="0.000000" />
            <ACTIONEVENT CLASSNAME="CActionEvent_AttackTiming" EVENTNAME="ATK_TIMING" TYPENAME="AtkTiming" EVENTTIME="0.240000" EVENTENDTIME="0.430000" ATK_POINT="10.000000" ATK_DIST="170.000000" ATK_RANGE="20.000000" IS_LAST_ATK="1" USEFANROUTINE="0" ATKRANGEBOX_MINX="-160.000000" ATKRANGEBOX_MINY="-140.000000" ATKRANGEBOX_MINZ="-600.000000" ATKRANGEBOX_MAXX="160.000000" ATKRANGEBOX_MAXY="320.000000" ATKRANGEBOX_MAXZ="-70.000000" TYPENUM="252800005" IS_WIDE_ATK="0" STUNTIME="0.000000" STATENAME="" />
            <ACTIONEVENT CLASSNAME="CActionEvent_Effect" EVENTNAME="Gozilla_Com_DP_E00" TYPENAME="Effect" EFFECTNAME="Gozilla_Com_DP_E00" OFFSETX="0.000000" OFFSETY="0.000000" OFFSETZ="0.000000" BILLX="0" BILLY="0" BILLZ="1" BILLBOARDX="1" BILLBOARDY="0" BILLBOARDALL="0" LOOP="0" BONENAME="" NEVERSTOP="0" TERMINATE="0" ALPHAGROUP="7" GRANDPARENT="0" EVENTTIME="0.000000" EVENTENDTIME="0.000000" />
            <ACTIONEVENT CLASSNAME="CActionEvent_LoopAni" EVENTNAME="TR_GODZILLA_COMBAT_WAIT" TYPENAME="LoopAnimation" ANIMATIONNAME="TR_GODZILLA_COMBAT_WAIT" WEIGHT="1.000000" DELAY="0.100000" EVENTTIME="0.000000" EVENTENDTIME="0.000000" />
            <ACTIONEVENT CLASSNAME="CActionEvent_Model" EVENTNAME="EYE04" TYPENAME="Model" MODELNAME="EYE04" SHOW="1" NORESHOW="0" EVENTTIME="0.000000" EVENTENDTIME="0.000000" />
            <ACTIONEVENT CLASSNAME="CActionEvent_Model" EVENTNAME="HEAD04" TYPENAME="Model" MODELNAME="HEAD04" SHOW="1" NORESHOW="0" EVENTTIME="0.000000" EVENTENDTIME="0.000000" />
            <ACTIONEVENT CLASSNAME="CActionEvent_Move" EVENTNAME="MOVE" TYPENAME="Movement" LENGTH="150.000000" SPEED="15.000000" ACCEL="0.000000" INVERSE="0" MOVEPLUS="0" CHARDIRPLUS="0" IGNORECOLLISION="0" EVENTTIME="0.150000" EVENTENDTIME="0.000000" />
            <ACTIONEVENT CLASSNAME="CActionEvent_Sound" EVENTNAME="TR_GODZILLA_COMB_DA_P_1" TYPENAME="Sound" SOUNDNAME="TR_GODZILLA_COMB_DA_P_1" VOLUME="255" LOOP="0" EVENTTIME="0.000000" EVENTENDTIME="0.000000" />
        </COMMAND>
        <COMMAND NAME="TR_PTERA_COMB_K" LOOP="0" TOTALTIME="0.800000">
            <ACTIONEVENT CLASSNAME="CActionEvent_ActionAni" EVENTNAME="TR_GODZILLA_COMB_K" TYPENAME="ActionAnimation" ANIMATIONNAME="TR_GODZILLA_COMB_K" FADEIN="0.100000" FADEOUT="0.100000" WEIGHT="1.000000" EVENTTIME="0.000000" EVENTENDTIME="0.000000" />
            <ACTIONEVENT CLASSNAME="CActionEvent_AttackTiming" EVENTNAME="ATK_TIMING" TYPENAME="AtkTiming" EVENTTIME="0.370000" EVENTENDTIME="0.670000" ATK_POINT="15.000000" ATK_DIST="170.000000" ATK_RANGE="20.000000" IS_LAST_ATK="0" USEFANROUTINE="0" ATKRANGEBOX_MINX="-200.000000" ATKRANGEBOX_MINY="-120.000000" ATKRANGEBOX_MINZ="-400.000000" ATKRANGEBOX_MAXX="200.000000" ATKRANGEBOX_MAXY="180.000000" ATKRANGEBOX_MAXZ="0.000000" TYPENUM="252800005" IS_WIDE_ATK="0" STUNTIME="0.000000" STATENAME="" />
            <ACTIONEVENT CLASSNAME="CActionEvent_Effect" EVENTNAME="Gozilla_Com_K_E00" TYPENAME="Effect" EFFECTNAME="Gozilla_Com_K_E00" OFFSETX="0.000000" OFFSETY="0.000000" OFFSETZ="0.000000" BILLX="0" BILLY="0" BILLZ="1" BILLBOARDX="1" BILLBOARDY="0" BILLBOARDALL="0" LOOP="0" BONENAME="" NEVERSTOP="0" TERMINATE="0" ALPHAGROUP="7" GRANDPARENT="0" EVENTTIME="0.000000" EVENTENDTIME="0.000000" />
            <ACTIONEVENT CLASSNAME="CActionEvent_Effect" EVENTNAME="Gozilla_Com_K_E01" TYPENAME="Effect" EFFECTNAME="Gozilla_Com_K_E01" OFFSETX="0.000000" OFFSETY="0.000000" OFFSETZ="0.000000" BILLX="0" BILLY="0" BILLZ="1" BILLBOARDX="1" BILLBOARDY="0" BILLBOARDALL="0" LOOP="0" BONENAME="" NEVERSTOP="0" TERMINATE="0" ALPHAGROUP="7" GRANDPARENT="0" EVENTTIME="0.000000" EVENTENDTIME="0.000000" />
            <ACTIONEVENT CLASSNAME="CActionEvent_Effect" EVENTNAME="Gozilla_Com_K_E02" TYPENAME="Effect" EFFECTNAME="Gozilla_Com_K_E02" OFFSETX="0.000000" OFFSETY="0.000000" OFFSETZ="0.000000" BILLX="0" BILLY="0" BILLZ="1" BILLBOARDX="1" BILLBOARDY="0" BILLBOARDALL="0" LOOP="0" BONENAME="" NEVERSTOP="0" TERMINATE="0" ALPHAGROUP="7" GRANDPARENT="0" EVENTTIME="0.000000" EVENTENDTIME="0.000000" />
            <ACTIONEVENT CLASSNAME="CActionEvent_LoopAni" EVENTNAME="TR_GODZILLA_COMBAT_WAIT" TYPENAME="LoopAnimation" ANIMATIONNAME="TR_GODZILLA_COMBAT_WAIT" WEIGHT="1.000000" DELAY="0.100000" EVENTTIME="0.000000" EVENTENDTIME="0.000000" />
            <ACTIONEVENT CLASSNAME="CActionEvent_Model" EVENTNAME="EYE04" TYPENAME="Model" MODELNAME="EYE04" SHOW="1" NORESHOW="0" EVENTTIME="0.000000" EVENTENDTIME="0.000000" />
            <ACTIONEVENT CLASSNAME="CActionEvent_Model" EVENTNAME="HEAD04" TYPENAME="Model" MODELNAME="HEAD04" SHOW="1" NORESHOW="0" EVENTTIME="0.000000" EVENTENDTIME="0.000000" />
            <ACTIONEVENT CLASSNAME="CActionEvent_Move" EVENTNAME="MOVE" TYPENAME="Movement" LENGTH="50.000000" SPEED="10.000000" ACCEL="0.000000" INVERSE="0" MOVEPLUS="0" CHARDIRPLUS="0" IGNORECOLLISION="0" EVENTTIME="0.300000" EVENTENDTIME="0.000000" />
            <ACTIONEVENT CLASSNAME="CActionEvent_Sound" EVENTNAME="TR_GODZILLA_COMB_K_1" TYPENAME="Sound" SOUNDNAME="TR_GODZILLA_COMB_K_1" VOLUME="200" LOOP="0" EVENTTIME="0.240000" EVENTENDTIME="0.000000" />
        </COMMAND>
        <COMMAND NAME="TR_PTERA_COMB_P" LOOP="0" TOTALTIME="0.520000">
            <ACTIONEVENT CLASSNAME="CActionEvent_ActionAni" EVENTNAME="TR_GODZILLA_COMB_P" TYPENAME="ActionAnimation" ANIMATIONNAME="TR_GODZILLA_COMB_P" FADEIN="0.100000" FADEOUT="0.100000" WEIGHT="1.000000" EVENTTIME="0.000000" EVENTENDTIME="0.000000" />
            <ACTIONEVENT CLASSNAME="CActionEvent_AttackTiming" EVENTNAME="ATK_TIMING" TYPENAME="AtkTiming" EVENTTIME="0.180000" EVENTENDTIME="0.380000" ATK_POINT="15.000000" ATK_DIST="170.000000" ATK_RANGE="20.000000" IS_LAST_ATK="0" USEFANROUTINE="0" ATKRANGEBOX_MINX="-200.000000" ATKRANGEBOX_MINY="-160.000000" ATKRANGEBOX_MINZ="-350.000000" ATKRANGEBOX_MAXX="200.000000" ATKRANGEBOX_MAXY="350.000000" ATKRANGEBOX_MAXZ="50.000000" TYPENUM="252800005" IS_WIDE_ATK="0" STUNTIME="0.000000" STATENAME="" />
            <ACTIONEVENT CLASSNAME="CActionEvent_Effect" EVENTNAME="Gozilla_Com_P_E00" TYPENAME="Effect" EFFECTNAME="Gozilla_Com_P_E00" OFFSETX="0.000000" OFFSETY="0.000000" OFFSETZ="0.000000" BILLX="0" BILLY="0" BILLZ="1" BILLBOARDX="1" BILLBOARDY="0" BILLBOARDALL="0" LOOP="0" BONENAME="" NEVERSTOP="0" TERMINATE="0" ALPHAGROUP="7" GRANDPARENT="0" EVENTTIME="0.000000" EVENTENDTIME="0.000000" />
            <ACTIONEVENT CLASSNAME="CActionEvent_EnableComboKey" EVENTNAME="COMBO_TIMING" TYPENAME="ComboTiming" EVENTTIME="0.000000" EVENTENDTIME="0.450000" />
            <ACTIONEVENT CLASSNAME="CActionEvent_LoopAni" EVENTNAME="TR_GODZILLA_COMBAT_WAIT" TYPENAME="LoopAnimation" ANIMATIONNAME="TR_GODZILLA_COMBAT_WAIT" WEIGHT="1.000000" DELAY="0.100000" EVENTTIME="0.000000" EVENTENDTIME="0.000000" />
            <ACTIONEVENT CLASSNAME="CActionEvent_Model" EVENTNAME="EYE04" TYPENAME="Model" MODELNAME="EYE04" SHOW="1" NORESHOW="0" EVENTTIME="0.000000" EVENTENDTIME="0.000000" />
            <ACTIONEVENT CLASSNAME="CActionEvent_Model" EVENTNAME="HEAD04" TYPENAME="Model" MODELNAME="HEAD04" SHOW="1" NORESHOW="0" EVENTTIME="0.000000" EVENTENDTIME="0.000000" />
            <ACTIONEVENT CLASSNAME="CActionEvent_Move" EVENTNAME="MOVE" TYPENAME="Movement" LENGTH="50.000000" SPEED="5.000000" ACCEL="0.000000" INVERSE="0" MOVEPLUS="0" CHARDIRPLUS="0" IGNORECOLLISION="0" EVENTTIME="0.200000" EVENTENDTIME="0.000000" />
            <ACTIONEVENT CLASSNAME="CActionEvent_Sound" EVENTNAME="GARU_COMB_JA_K_1" TYPENAME="Sound" SOUNDNAME="GARU_COMB_JA_K_1" VOLUME="255" LOOP="0" EVENTTIME="0.050000" EVENTENDTIME="0.000000" />
        </COMMAND>
        <COMMAND NAME="TR_PTERA_COMB_PP" LOOP="0" TOTALTIME="0.700000">
            <ACTIONEVENT CLASSNAME="CActionEvent_ActionAni" EVENTNAME="TR_GODZILLA_COMB_PP" TYPENAME="ActionAnimation" ANIMATIONNAME="TR_GODZILLA_COMB_PP" FADEIN="0.100000" FADEOUT="0.100000" WEIGHT="1.000000" EVENTTIME="0.000000" EVENTENDTIME="0.000000" />
            <ACTIONEVENT CLASSNAME="CActionEvent_AttackTiming" EVENTNAME="ATK_TIMING" TYPENAME="AtkTiming" EVENTTIME="0.240000" EVENTENDTIME="0.500000" ATK_POINT="20.000000" ATK_DIST="170.000000" ATK_RANGE="20.000000" IS_LAST_ATK="1" USEFANROUTINE="0" ATKRANGEBOX_MINX="-230.000000" ATKRANGEBOX_MINY="-160.000000" ATKRANGEBOX_MINZ="-370.000000" ATKRANGEBOX_MAXX="230.000000" ATKRANGEBOX_MAXY="350.000000" ATKRANGEBOX_MAXZ="50.000000" TYPENUM="252800005" IS_WIDE_ATK="0" STUNTIME="0.000000" STATENAME="" />
            <ACTIONEVENT CLASSNAME="CActionEvent_Effect" EVENTNAME="Gozilla_Com_PP_E00" TYPENAME="Effect" EFFECTNAME="Gozilla_Com_PP_E00" OFFSETX="0.000000" OFFSETY="0.000000" OFFSETZ="0.000000" BILLX="0" BILLY="0" BILLZ="1" BILLBOARDX="1" BILLBOARDY="0" BILLBOARDALL="0" LOOP="0" BONENAME="" NEVERSTOP="0" TERMINATE="0" ALPHAGROUP="7" GRANDPARENT="0" EVENTTIME="0.000000" EVENTENDTIME="0.000000" />
            <ACTIONEVENT CLASSNAME="CActionEvent_LoopAni" EVENTNAME="TR_GODZILLA_COMBAT_WAIT" TYPENAME="LoopAnimation" ANIMATIONNAME="TR_GODZILLA_COMBAT_WAIT" WEIGHT="1.000000" DELAY="0.100000" EVENTTIME="0.000000" EVENTENDTIME="0.000000" />
            <ACTIONEVENT CLASSNAME="CActionEvent_Model" EVENTNAME="EYE04" TYPENAME="Model" MODELNAME="EYE04" SHOW="1" NORESHOW="0" EVENTTIME="0.000000" EVENTENDTIME="0.000000" />
            <ACTIONEVENT CLASSNAME="CActionEvent_Model" EVENTNAME="HEAD04" TYPENAME="Model" MODELNAME="HEAD04" SHOW="1" NORESHOW="0" EVENTTIME="0.000000" EVENTENDTIME="0.000000" />
            <ACTIONEVENT CLASSNAME="CActionEvent_Move" EVENTNAME="MOVE" TYPENAME="Movement" LENGTH="70.000000" SPEED="5.000000" ACCEL="0.000000" INVERSE="0" MOVEPLUS="0" CHARDIRPLUS="0" IGNORECOLLISION="0" EVENTTIME="0.200000" EVENTENDTIME="0.000000" />
            <ACTIONEVENT CLASSNAME="CActionEvent_Sound" EVENTNAME="GARU_COMB_ESC_1" TYPENAME="Sound" SOUNDNAME="GARU_COMB_ESC_1" VOLUME="255" LOOP="0" EVENTTIME="0.150000" EVENTENDTIME="0.000000" />
        </COMMAND>
        <COMMAND NAME="TR_PTERA_COMB_TRATK" LOOP="0" TOTALTIME="0.330000">
            <ACTIONEVENT CLASSNAME="CActionEvent_ActionAni" EVENTNAME="Taru_Comb_PP_01" TYPENAME="ActionAnimation" ANIMATIONNAME="Taru_Comb_PP_01" FADEIN="0.100000" FADEOUT="0.000000" WEIGHT="1.000000" EVENTTIME="0.000000" EVENTENDTIME="0.000000" />
            <ACTIONEVENT CLASSNAME="CActionEvent_AttackTiming" EVENTNAME="ATK_TIMING" TYPENAME="AtkTiming" EVENTTIME="0.090000" EVENTENDTIME="0.180000" ATK_POINT="-10.000000" ATK_DIST="170.000000" ATK_RANGE="25.000000" IS_LAST_ATK="0" USEFANROUTINE="0" ATKRANGEBOX_MINX="-110.000000" ATKRANGEBOX_MINY="-140.000000" ATKRANGEBOX_MINZ="-170.000000" ATKRANGEBOX_MAXX="110.000000" ATKRANGEBOX_MAXY="180.000000" ATKRANGEBOX_MAXZ="30.000000" TYPENUM="252850005" IS_WIDE_ATK="0" STUNTIME="0.000000" STATENAME="" />
            <ACTIONEVENT CLASSNAME="CActionEvent_Model" EVENTNAME="EYE04" TYPENAME="Model" MODELNAME="EYE04" SHOW="1" NORESHOW="0" EVENTTIME="0.000000" EVENTENDTIME="0.000000" />
            <ACTIONEVENT CLASSNAME="CActionEvent_Model" EVENTNAME="HEAD04" TYPENAME="Model" MODELNAME="HEAD04" SHOW="1" NORESHOW="0" EVENTTIME="0.000000" EVENTENDTIME="0.000000" />
            <ACTIONEVENT CLASSNAME="CActionEvent_Move" EVENTNAME="MOVE01" TYPENAME="Movement" LENGTH="80.000000" SPEED="15.000000" ACCEL="0.000000" INVERSE="0" MOVEPLUS="0" CHARDIRPLUS="0" IGNORECOLLISION="0" EVENTTIME="0.100000" EVENTENDTIME="0.000000" />
            <ACTIONEVENT CLASSNAME="CActionEvent_NextCommand" EVENTNAME="NEXT_COMMAND" TYPENAME="NextCommand" NEXTCOMMAND="TR_PTERA_COMB_TRATK_01" EVENTTIME="0.320000" EVENTENDTIME="0.000000" />
            <ACTIONEVENT CLASSNAME="CActionEvent_Sound" EVENTNAME="TARU_COMB_PPP_02_S1" TYPENAME="Sound" SOUNDNAME="TARU_COMB_PPP_02_S1" VOLUME="220" LOOP="0" EVENTTIME="0.000000" EVENTENDTIME="0.000000" />
        </COMMAND>
        <COMMAND NAME="TR_PTERA_COMB_TRATK_01" LOOP="0" TOTALTIME="0.270000">
            <ACTIONEVENT CLASSNAME="CActionEvent_ActionAni" EVENTNAME="Taru_Comb_PP_02" TYPENAME="ActionAnimation" ANIMATIONNAME="Taru_Comb_PP_02" FADEIN="0.000000" FADEOUT="0.100000" WEIGHT="1.000000" EVENTTIME="0.000000" EVENTENDTIME="0.000000" />
            <ACTIONEVENT CLASSNAME="CActionEvent_AttackTiming" EVENTNAME="ATK_TIMING" TYPENAME="AtkTiming" EVENTTIME="0.000000" EVENTENDTIME="0.150000" ATK_POINT="60.000000" ATK_DIST="170.000000" ATK_RANGE="20.000000" IS_LAST_ATK="0" USEFANROUTINE="0" ATKRANGEBOX_MINX="-110.000000" ATKRANGEBOX_MINY="-140.000000" ATKRANGEBOX_MINZ="-180.000000" ATKRANGEBOX_MAXX="110.000000" ATKRANGEBOX_MAXY="180.000000" ATKRANGEBOX_MAXZ="30.000000" TYPENUM="252850005" IS_WIDE_ATK="0" STUNTIME="0.000000" STATENAME="" />
            <ACTIONEVENT CLASSNAME="CActionEvent_Move" EVENTNAME="MOVE" TYPENAME="Movement" LENGTH="80.000000" SPEED="15.000000" ACCEL="0.000000" INVERSE="0" MOVEPLUS="0" CHARDIRPLUS="0" IGNORECOLLISION="0" EVENTTIME="0.000000" EVENTENDTIME="0.000000" />
            <ACTIONEVENT CLASSNAME="CActionEvent_NextCommand" EVENTNAME="NEXT_COMMAND" TYPENAME="NextCommand" NEXTCOMMAND="TR_PTERA_COMB_TRATK_02" EVENTTIME="0.270000" EVENTENDTIME="0.000000" />
            <ACTIONEVENT CLASSNAME="CActionEvent_Sound" EVENTNAME="TARU_COMB_PPP_02_S2" TYPENAME="Sound" SOUNDNAME="TARU_COMB_PPP_02_S2" VOLUME="255" LOOP="0" EVENTTIME="0.000000" EVENTENDTIME="0.000000" />
        </COMMAND>
        <COMMAND NAME="TR_PTERA_COMB_TRATK_02" LOOP="0" TOTALTIME="0.330000">
            <ACTIONEVENT CLASSNAME="CActionEvent_ActionAni" EVENTNAME="Taru_Comb_PP_01" TYPENAME="ActionAnimation" ANIMATIONNAME="Taru_Comb_PP_01" FADEIN="0.100000" FADEOUT="0.000000" WEIGHT="1.000000" EVENTTIME="0.000000" EVENTENDTIME="0.000000" />
            <ACTIONEVENT CLASSNAME="CActionEvent_AttackTiming" EVENTNAME="ATK_TIMING" TYPENAME="AtkTiming" EVENTTIME="0.090000" EVENTENDTIME="0.180000" ATK_POINT="-10.000000" ATK_DIST="170.000000" ATK_RANGE="25.000000" IS_LAST_ATK="0" USEFANROUTINE="0" ATKRANGEBOX_MINX="-110.000000" ATKRANGEBOX_MINY="-140.000000" ATKRANGEBOX_MINZ="-170.000000" ATKRANGEBOX_MAXX="110.000000" ATKRANGEBOX_MAXY="180.000000" ATKRANGEBOX_MAXZ="30.000000" TYPENUM="252850005" IS_WIDE_ATK="0" STUNTIME="0.000000" STATENAME="" />
            <ACTIONEVENT CLASSNAME="CActionEvent_Model" EVENTNAME="EYE04" TYPENAME="Model" MODELNAME="EYE04" SHOW="1" NORESHOW="0" EVENTTIME="0.000000" EVENTENDTIME="0.000000" />
            <ACTIONEVENT CLASSNAME="CActionEvent_Model" EVENTNAME="HEAD04" TYPENAME="Model" MODELNAME="HEAD04" SHOW="1" NORESHOW="0" EVENTTIME="0.000000" EVENTENDTIME="0.000000" />
            <ACTIONEVENT CLASSNAME="CActionEvent_Move" EVENTNAME="MOVE01" TYPENAME="Movement" LENGTH="80.000000" SPEED="15.000000" ACCEL="0.000000" INVERSE="0" MOVEPLUS="0" CHARDIRPLUS="0" IGNORECOLLISION="0" EVENTTIME="0.100000" EVENTENDTIME="0.000000" />
            <ACTIONEVENT CLASSNAME="CActionEvent_NextCommand" EVENTNAME="NEXT_COMMAND" TYPENAME="NextCommand" NEXTCOMMAND="TR_PTERA_COMB_TRATK_03" EVENTTIME="0.320000" EVENTENDTIME="0.000000" />
            <ACTIONEVENT CLASSNAME="CActionEvent_Sound" EVENTNAME="TARU_COMB_PPP_02_S1" TYPENAME="Sound" SOUNDNAME="TARU_COMB_PPP_02_S1" VOLUME="220" LOOP="0" EVENTTIME="0.000000" EVENTENDTIME="0.000000" />
        </COMMAND>
        <COMMAND NAME="TR_PTERA_COMB_TRATK_03" LOOP="0" TOTALTIME="0.750000">
            <ACTIONEVENT CLASSNAME="CActionEvent_ActionAni" EVENTNAME="COMB_DA_P" TYPENAME="ActionAnimation" ANIMATIONNAME="COMB_DA_P" FADEIN="0.100000" FADEOUT="0.100000" WEIGHT="1.000000" EVENTTIME="0.000000" EVENTENDTIME="0.000000" />
            <ACTIONEVENT CLASSNAME="CActionEvent_AttackTiming" EVENTNAME="ATKTIMING" TYPENAME="AtkTiming" EVENTTIME="0.100000" EVENTENDTIME="0.650000" ATK_POINT="-20.000000" ATK_DIST="170.000000" ATK_RANGE="25.000000" IS_LAST_ATK="1" USEFANROUTINE="0" ATKRANGEBOX_MINX="-110.000000" ATKRANGEBOX_MINY="-140.000000" ATKRANGEBOX_MINZ="-250.000000" ATKRANGEBOX_MAXX="110.000000" ATKRANGEBOX_MAXY="160.000000" ATKRANGEBOX_MAXZ="30.000000" TYPENUM="252850005" IS_WIDE_ATK="0" STUNTIME="0.000000" STATENAME="" />
            <ACTIONEVENT CLASSNAME="CActionEvent_LoopAni" EVENTNAME="TR_GODZILLA_COMBAT_WAIT" TYPENAME="LoopAnimation" ANIMATIONNAME="TR_GODZILLA_COMBAT_WAIT" WEIGHT="1.000000" DELAY="0.100000" EVENTTIME="0.000000" EVENTENDTIME="0.000000" />
            <ACTIONEVENT CLASSNAME="CActionEvent_Model" EVENTNAME="EYE04" TYPENAME="Model" MODELNAME="EYE04" SHOW="1" NORESHOW="0" EVENTTIME="0.000000" EVENTENDTIME="0.000000" />
            <ACTIONEVENT CLASSNAME="CActionEvent_Model" EVENTNAME="HEAD04" TYPENAME="Model" MODELNAME="HEAD04" SHOW="1" NORESHOW="0" EVENTTIME="0.000000" EVENTENDTIME="0.000000" />
            <ACTIONEVENT CLASSNAME="CActionEvent_Move" EVENTNAME="MOVE" TYPENAME="Movement" LENGTH="220.000000" SPEED="15.000000" ACCEL="0.000000" INVERSE="0" MOVEPLUS="0" CHARDIRPLUS="0" IGNORECOLLISION="0" EVENTTIME="0.150000" EVENTENDTIME="0.000000" />
            <ACTIONEVENT CLASSNAME="CActionEvent_Sound" EVENTNAME="TARU_JUMP_LAND_S1" TYPENAME="Sound" SOUNDNAME="TARU_JUMP_LAND_S1" VOLUME="120" LOOP="0" EVENTTIME="0.410000" EVENTENDTIME="0.000000" />
            <ACTIONEVENT CLASSNAME="CActionEvent_Sound" EVENTNAME="TARU_DA_P_S1" TYPENAME="Sound" SOUNDNAME="TARU_DA_P_S1" VOLUME="200" LOOP="0" EVENTTIME="0.000000" EVENTENDTIME="0.000000" />
            <ACTIONEVENT CLASSNAME="CActionEvent_Sound" EVENTNAME="TARU_JA_K_S1" TYPENAME="Sound" SOUNDNAME="TARU_JA_K_S1" VOLUME="180" LOOP="0" EVENTTIME="0.000000" EVENTENDTIME="0.000000" />
        </COMMAND>
        <COMMAND NAME="TR_PTERA_DASH_01" LOOP="0" TOTALTIME="10.000000">
            <ACTIONEVENT CLASSNAME="CActionEvent_LoopAni" EVENTNAME="TR_GODZILLA_DASH_01" TYPENAME="LoopAnimation" ANIMATIONNAME="TR_GODZILLA_DASH_01" WEIGHT="1.000000" DELAY="0.100000" EVENTTIME="0.000000" EVENTENDTIME="0.000000" />
            <ACTIONEVENT CLASSNAME="CActionEvent_Model" EVENTNAME="EYE09" TYPENAME="Model" MODELNAME="EYE09" SHOW="1" NORESHOW="0" EVENTTIME="0.000000" EVENTENDTIME="0.000000" />
            <ACTIONEVENT CLASSNAME="CActionEvent_Model" EVENTNAME="HEAD09" TYPENAME="Model" MODELNAME="HEAD09" SHOW="1" NORESHOW="0" EVENTTIME="0.000000" EVENTENDTIME="0.000000" />
        </COMMAND>
        <COMMAND NAME="TR_PTERA_DASH_02" LOOP="0" TOTALTIME="10.000000">
            <ACTIONEVENT CLASSNAME="CActionEvent_LoopAni" EVENTNAME="TR_GODZILLA_DASH_02" TYPENAME="LoopAnimation" ANIMATIONNAME="TR_GODZILLA_DASH_02" WEIGHT="1.000000" DELAY="0.100000" EVENTTIME="0.000000" EVENTENDTIME="0.000000" />
            <ACTIONEVENT CLASSNAME="CActionEvent_Model" EVENTNAME="EYE10" TYPENAME="Model" MODELNAME="EYE10" SHOW="1" NORESHOW="0" EVENTTIME="0.000000" EVENTENDTIME="0.000000" />
            <ACTIONEVENT CLASSNAME="CActionEvent_Model" EVENTNAME="HEAD10" TYPENAME="Model" MODELNAME="HEAD10" SHOW="1" NORESHOW="0" EVENTTIME="0.000000" EVENTENDTIME="0.000000" />
        </COMMAND>
        <COMMAND NAME="TR_PTERA_IDLE_01" LOOP="0" TOTALTIME="0.830000">
            <ACTIONEVENT CLASSNAME="CActionEvent_ActionAni" EVENTNAME="Ptera_Com_IDLE_01" TYPENAME="ActionAnimation" ANIMATIONNAME="Ptera_Com_IDLE_01" FADEIN="0.100000" FADEOUT="0.100000" WEIGHT="1.000000" EVENTTIME="0.000000" EVENTENDTIME="0.000000" />
            <ACTIONEVENT CLASSNAME="CActionEvent_Effect" EVENTNAME="KidGrio_comb_SPE1_B00" TYPENAME="Effect" EFFECTNAME="KidGrio_comb_SPE1_B00" OFFSETX="0.000000" OFFSETY="400.000000" OFFSETZ="0.000000" BILLX="0" BILLY="1" BILLZ="0" BILLBOARDX="0" BILLBOARDY="0" BILLBOARDALL="1" LOOP="0" BONENAME="" NEVERSTOP="0" TERMINATE="0" ALPHAGROUP="7" GRANDPARENT="0" EVENTTIME="0.200000" EVENTENDTIME="0.000000" />
            <ACTIONEVENT CLASSNAME="CActionEvent_LoopAni" EVENTNAME="TR_GODZILLA_COMBAT_WAIT" TYPENAME="LoopAnimation" ANIMATIONNAME="TR_GODZILLA_COMBAT_WAIT" WEIGHT="1.000000" DELAY="0.100000" EVENTTIME="0.000000" EVENTENDTIME="0.000000" />
            <ACTIONEVENT CLASSNAME="CActionEvent_Model" EVENTNAME="EYE01" TYPENAME="Model" MODELNAME="EYE01" SHOW="1" NORESHOW="0" EVENTTIME="0.000000" EVENTENDTIME="0.000000" />
            <ACTIONEVENT CLASSNAME="CActionEvent_Model" EVENTNAME="HEAD01" TYPENAME="Model" MODELNAME="HEAD01" SHOW="1" NORESHOW="0" EVENTTIME="0.000000" EVENTENDTIME="0.000000" />
            <ACTIONEVENT CLASSNAME="CActionEvent_Sound" EVENTNAME="CM_DASH_02" TYPENAME="Sound" SOUNDNAME="CM_DASH_02" VOLUME="255" LOOP="0" EVENTTIME="0.000000" EVENTENDTIME="0.000000" />
        </COMMAND>
        <COMMAND NAME="TR_PTERA_JUMP_DOWN" LOOP="0" TOTALTIME="0.830000">
            <ACTIONEVENT CLASSNAME="CActionEvent_ActionAni" EVENTNAME="TR_GODZILLA_JUMP_DOWN" TYPENAME="ActionAnimation" ANIMATIONNAME="TR_GODZILLA_JUMP_DOWN" FADEIN="0.100000" FADEOUT="0.100000" WEIGHT="1.000000" EVENTTIME="0.000000" EVENTENDTIME="0.000000" />
            <ACTIONEVENT CLASSNAME="CActionEvent_Model" EVENTNAME="EYE06" TYPENAME="Model" MODELNAME="EYE06" SHOW="1" NORESHOW="0" EVENTTIME="0.000000" EVENTENDTIME="0.000000" />
            <ACTIONEVENT CLASSNAME="CActionEvent_Model" EVENTNAME="HEAD06" TYPENAME="Model" MODELNAME="HEAD06" SHOW="1" NORESHOW="0" EVENTTIME="0.000000" EVENTENDTIME="0.000000" />
            <ACTIONEVENT CLASSNAME="CActionEvent_Sound" EVENTNAME="TR_GODZILLA_JUMP_DOWN_1" TYPENAME="Sound" SOUNDNAME="TR_GODZILLA_JUMP_DOWN_1" VOLUME="255" LOOP="0" EVENTTIME="0.000000" EVENTENDTIME="0.000000" />
        </COMMAND>
        <COMMAND NAME="TR_PTERA_JUMP_LAND" LOOP="0" TOTALTIME="0.800000">
            <ACTIONEVENT CLASSNAME="CActionEvent_ActionAni" EVENTNAME="TR_GODZILLA_JUMP_LAND" TYPENAME="ActionAnimation" ANIMATIONNAME="TR_GODZILLA_JUMP_LAND" FADEIN="0.100000" FADEOUT="0.100000" WEIGHT="1.000000" EVENTTIME="0.000000" EVENTENDTIME="0.000000" />
            <ACTIONEVENT CLASSNAME="CActionEvent_AttackTiming" EVENTNAME="ATK_TIMING" TYPENAME="AtkTiming" EVENTTIME="0.000000" EVENTENDTIME="0.000000" ATK_POINT="-5.000000" ATK_DIST="170.000000" ATK_RANGE="20.000000" IS_LAST_ATK="0" USEFANROUTINE="0" ATKRANGEBOX_MINX="-280.000000" ATKRANGEBOX_MINY="-160.000000" ATKRANGEBOX_MINZ="-280.000000" ATKRANGEBOX_MAXX="280.000000" ATKRANGEBOX_MAXY="140.000000" ATKRANGEBOX_MAXZ="280.000000" TYPENUM="252800005" IS_WIDE_ATK="0" STUNTIME="0.000000" STATENAME="" />
            <ACTIONEVENT CLASSNAME="CActionEvent_Effect" EVENTNAME="Gozilla_Com_JL_E00" TYPENAME="Effect" EFFECTNAME="Gozilla_Com_JL_E00" OFFSETX="0.000000" OFFSETY="0.000000" OFFSETZ="0.000000" BILLX="0" BILLY="0" BILLZ="1" BILLBOARDX="0" BILLBOARDY="1" BILLBOARDALL="0" LOOP="0" BONENAME="" NEVERSTOP="0" TERMINATE="0" ALPHAGROUP="7" GRANDPARENT="0" EVENTTIME="0.000000" EVENTENDTIME="0.000000" />
            <ACTIONEVENT CLASSNAME="CActionEvent_Effect" EVENTNAME="Gozilla_Com_JL_E01" TYPENAME="Effect" EFFECTNAME="Gozilla_Com_JL_E01" OFFSETX="0.000000" OFFSETY="0.000000" OFFSETZ="0.000000" BILLX="0" BILLY="0" BILLZ="1" BILLBOARDX="0" BILLBOARDY="1" BILLBOARDALL="0" LOOP="0" BONENAME="" NEVERSTOP="0" TERMINATE="0" ALPHAGROUP="7" GRANDPARENT="0" EVENTTIME="0.000000" EVENTENDTIME="0.000000" />
            <ACTIONEVENT CLASSNAME="CActionEvent_Effect" EVENTNAME="Gozilla_Com_JL_E02" TYPENAME="Effect" EFFECTNAME="Gozilla_Com_JL_E02" OFFSETX="0.000000" OFFSETY="0.000000" OFFSETZ="0.000000" BILLX="0" BILLY="0" BILLZ="1" BILLBOARDX="0" BILLBOARDY="1" BILLBOARDALL="0" LOOP="0" BONENAME="" NEVERSTOP="0" TERMINATE="0" ALPHAGROUP="7" GRANDPARENT="0" EVENTTIME="0.000000" EVENTENDTIME="0.000000" />
            <ACTIONEVENT CLASSNAME="CActionEvent_LoopAni" EVENTNAME="TR_GODZILLA_COMBAT_WAIT" TYPENAME="LoopAnimation" ANIMATIONNAME="TR_GODZILLA_COMBAT_WAIT" WEIGHT="1.000000" DELAY="0.100000" EVENTTIME="0.000000" EVENTENDTIME="0.000000" />
            <ACTIONEVENT CLASSNAME="CActionEvent_Model" EVENTNAME="EYE06" TYPENAME="Model" MODELNAME="EYE06" SHOW="1" NORESHOW="0" EVENTTIME="0.000000" EVENTENDTIME="0.000000" />
            <ACTIONEVENT CLASSNAME="CActionEvent_Model" EVENTNAME="HEAD06" TYPENAME="Model" MODELNAME="HEAD06" SHOW="1" NORESHOW="0" EVENTTIME="0.000000" EVENTENDTIME="0.000000" />
            <ACTIONEVENT CLASSNAME="CActionEvent_Particle" EVENTNAME="Gozilla_obj_JL_P00" TYPENAME="Particle" PARTICLENAME="GODZILLA_JUMP_LAND_P00" OFFSETX="0.000000" OFFSETY="0.000000" OFFSETZ="0.000000" USEBONE="0" BONENAME="" TERMINATE="0" EVENTTIME="0.070000" EVENTENDTIME="0.000000" />
            <ACTIONEVENT CLASSNAME="CActionEvent_Sound" EVENTNAME="TR_GODZILLA_JUMP_LAND_1" TYPENAME="Sound" SOUNDNAME="TR_GODZILLA_JUMP_LAND_1" VOLUME="255" LOOP="0" EVENTTIME="0.000000" EVENTENDTIME="0.000000" />
        </COMMAND>
        <COMMAND NAME="TR_PTERA_JUMP_UP" LOOP="0" TOTALTIME="10.000000">
            <ACTIONEVENT CLASSNAME="CActionEvent_LoopAni" EVENTNAME="TR_GODZILLA_JUMP_UP" TYPENAME="LoopAnimation" ANIMATIONNAME="TR_GODZILLA_JUMP_UP" WEIGHT="1.000000" DELAY="0.100000" EVENTTIME="0.000000" EVENTENDTIME="0.000000" />
            <ACTIONEVENT CLASSNAME="CActionEvent_Model" EVENTNAME="EYE06" TYPENAME="Model" MODELNAME="EYE06" SHOW="1" NORESHOW="0" EVENTTIME="0.000000" EVENTENDTIME="0.000000" />
            <ACTIONEVENT CLASSNAME="CActionEvent_Model" EVENTNAME="HEAD06" TYPENAME="Model" MODELNAME="HEAD06" SHOW="1" NORESHOW="0" EVENTTIME="0.000000" EVENTENDTIME="0.000000" />
        </COMMAND>
        <COMMAND NAME="TR_PTERA_MOVE_STOP" LOOP="0" TOTALTIME="1.000000">
            <ACTIONEVENT CLASSNAME="CActionEvent_ActionAni" EVENTNAME="TR_GODZILLA_MOVE_STOP" TYPENAME="ActionAnimation" ANIMATIONNAME="TR_GODZILLA_MOVE_STOP" FADEIN="0.100000" FADEOUT="0.100000" WEIGHT="1.000000" EVENTTIME="0.000000" EVENTENDTIME="0.000000" />
            <ACTIONEVENT CLASSNAME="CActionEvent_LoopAni" EVENTNAME="TR_GODZILLA_COMBAT_WAIT" TYPENAME="LoopAnimation" ANIMATIONNAME="TR_GODZILLA_COMBAT_WAIT" WEIGHT="1.000000" DELAY="0.100000" EVENTTIME="0.000000" EVENTENDTIME="0.000000" />
            <ACTIONEVENT CLASSNAME="CActionEvent_Model" EVENTNAME="EYE10" TYPENAME="Model" MODELNAME="EYE10" SHOW="1" NORESHOW="0" EVENTTIME="0.000000" EVENTENDTIME="0.000000" />
            <ACTIONEVENT CLASSNAME="CActionEvent_Model" EVENTNAME="HEAD10" TYPENAME="Model" MODELNAME="HEAD10" SHOW="1" NORESHOW="0" EVENTTIME="0.000000" EVENTENDTIME="0.000000" />
            <ACTIONEVENT CLASSNAME="CActionEvent_Sound" EVENTNAME="PURU_COMBO_ESC_1" TYPENAME="Sound" SOUNDNAME="PURU_COMBO_ESC_1" VOLUME="255" LOOP="0" EVENTTIME="0.000000" EVENTENDTIME="0.000000" />
        </COMMAND>
    </COMMAND_LIST>
</CHARACTER>
