<?xml version="1.0" encoding="utf-8"?>
<CreateItemProperty>
	<CreateItem Num="1" Name="司思骯腌" GetItemID="286000025" GetItemType="0" GetItemValue="7" GetPer="1000000" NeedItemNum="1" NeedItemID_1="850000000" NeedItemType_1="1" NeedItemVlaue_1="3" NeedItemID_2="0" NeedItemType_2="0" NeedItemValue_2="0" NeedItemID_3="0" NeedItemType_3="0" NeedItemValue_3="0" NeedMoney="1000" Hide="0"/>
	<CreateItem Num="2" Name="司思骯腌" GetItemID="286000026" GetItemType="0" GetItemValue="7" GetPer="1000000" NeedItemNum="2" NeedItemID_1="850000000" NeedItemType_1="1" NeedItemVlaue_1="3" NeedItemID_2="850000001" NeedItemType_2="1" NeedItemValue_2="1" NeedItemID_3="0" NeedItemType_3="0" NeedItemValue_3="0" NeedMoney="2000" Hide="0"/>
	<CreateItem Num="3" Name="司思骯腌" GetItemID="286000027" GetItemType="0" GetItemValue="7" GetPer="1000000" NeedItemNum="2" NeedItemID_1="850000000" NeedItemType_1="1" NeedItemVlaue_1="3" NeedItemID_2="850000002" NeedItemType_2="1" NeedItemValue_2="1" NeedItemID_3="0" NeedItemType_3="0" NeedItemValue_3="0" NeedMoney="3000" Hide="0"/>
	<CreateItem Num="4" Name="司思骯腌" GetItemID="286000029" GetItemType="0" GetItemValue="7" GetPer="1000000" NeedItemNum="2" NeedItemID_1="850000000" NeedItemType_1="1" NeedItemVlaue_1="3" NeedItemID_2="850000002" NeedItemType_2="1" NeedItemValue_2="1" NeedItemID_3="0" NeedItemType_3="0" NeedItemValue_3="0" NeedMoney="3000" Hide="0"/>
	<CreateItem Num="5" Name="司思骯腌" GetItemID="286000030" GetItemType="0" GetItemValue="7" GetPer="1000000" NeedItemNum="3" NeedItemID_1="850000000" NeedItemType_1="1" NeedItemVlaue_1="3" NeedItemID_2="850000001" NeedItemType_2="1" NeedItemValue_2="2" NeedItemID_3="850000002" NeedItemType_3="1" NeedItemValue_3="2" NeedMoney="4000" Hide="0"/>
	<CreateItem Num="6" Name="司思骯腌" GetItemID="286000031" GetItemType="0" GetItemValue="7" GetPer="1000000" NeedItemNum="3" NeedItemID_1="850000001" NeedItemType_1="1" NeedItemVlaue_1="3" NeedItemID_2="850000002" NeedItemType_2="1" NeedItemValue_2="2" NeedItemID_3="850000003" NeedItemType_3="1" NeedItemValue_3="3" NeedMoney="5000" Hide="0"/>
	<CreateItem Num="7" Name="司思骯腌" GetItemID="286000032" GetItemType="0" GetItemValue="7" GetPer="1000000" NeedItemNum="2" NeedItemID_1="850000000" NeedItemType_1="1" NeedItemVlaue_1="3" NeedItemID_2="850000001" NeedItemType_2="1" NeedItemValue_2="2" NeedItemID_3="0" NeedItemType_3="0" NeedItemValue_3="0" NeedMoney="2000" Hide="0"/>
	<CreateItem Num="8" Name="司思骯腌ON!" GetItemID="286000033" GetItemType="0" GetItemValue="7" GetPer="1000000" NeedItemNum="2" NeedItemID_1="850000000" NeedItemType_1="1" NeedItemVlaue_1="5" NeedItemID_2="0" NeedItemType_2="0" NeedItemValue_2="0" NeedItemID_3="0" NeedItemType_3="0" NeedItemValue_3="0" NeedMoney="2000" Hide="0" NeedItemType="0" NeedMoney_3="0"/>
	<CreateItem Num="9" Name="司思骯腌" GetItemID="286000034" GetItemType="0" GetItemValue="7" GetPer="1000000" NeedItemNum="3" NeedItemID_1="850000000" NeedItemType_1="1" NeedItemVlaue_1="5" NeedItemID_2="850000001" NeedItemType_2="1" NeedItemValue_2="2" NeedItemID_3="850000002" NeedItemType_3="1" NeedItemValue_3="2" NeedMoney="4000" Hide="0"/>
	<CreateItem Num="10" Name="司思骯腌" GetItemID="286000035" GetItemType="0" GetItemValue="7" GetPer="1000000" NeedItemNum="2" NeedItemID_1="850000000" NeedItemType_1="1" NeedItemVlaue_1="3" NeedItemID_2="850000001" NeedItemType_2="1" NeedItemValue_2="3" NeedItemID_3="0" NeedItemType_3="0" NeedItemValue_3="0" NeedMoney="2000" Hide="0"/>
	<CreateItem Num="11" Name="556司思骯腌" GetItemID="286000036" GetItemType="0" GetItemValue="7" GetPer="1000000" NeedItemNum="3" NeedItemID_1="850000000" NeedItemType_1="1" NeedItemVlaue_1="5" NeedItemID_2="850000001" NeedItemType_2="1" NeedItemValue_2="3" NeedItemID_3="850000002" NeedItemType_3="1" NeedItemValue_3="1" NeedMoney="4000" Hide="0"/>
	<CreateItem Num="12" Name="司思骯腌" GetItemID="286000037" GetItemType="0" GetItemValue="7" GetPer="1000000" NeedItemNum="3" NeedItemID_1="850000004" NeedItemType_1="1" NeedItemVlaue_1="3" NeedItemID_2="850000005" NeedItemType_2="1" NeedItemValue_2="3" NeedItemID_3="850000006" NeedItemType_3="1" NeedItemValue_3="3" NeedMoney="4000" Hide="0"/>
	<CreateItem Num="13" Name="司思骯腌" GetItemID="286000039" GetItemType="0" GetItemValue="7" GetPer="1000000" NeedItemNum="3" NeedItemID_1="850000003" NeedItemType_1="1" NeedItemVlaue_1="5" NeedItemID_2="850000007" NeedItemType_2="1" NeedItemValue_2="5" NeedItemID_3="850000008" NeedItemType_3="1" NeedItemValue_3="1" NeedMoney="5000" Hide="0"/>
	<CreateItem Num="14" Name="司思骯腌" GetItemID="286000040" GetItemType="0" GetItemValue="7" GetPer="1000000" NeedItemNum="3" NeedItemID_1="850000003" NeedItemType_1="1" NeedItemVlaue_1="5" NeedItemID_2="850000007" NeedItemType_2="1" NeedItemValue_2="5" NeedItemID_3="850000008" NeedItemType_3="1" NeedItemValue_3="5" NeedMoney="5000" Hide="0"/>
	<CreateItem Num="15" Name="司思骯腌" GetItemID="286000041" GetItemType="0" GetItemValue="7" GetPer="1000000" NeedItemNum="2" NeedItemID_1="850000006" NeedItemType_1="1" NeedItemVlaue_1="5" NeedItemID_2="850001003" NeedItemType_2="1" NeedItemValue_2="2" NeedItemID_3="0" NeedItemType_3="0" NeedItemValue_3="0" NeedMoney="3000" Hide="0"/>
	<CreateItem Num="16" Name="司思骯腌" GetItemID="286000042" GetItemType="0" GetItemValue="7" GetPer="1000000" NeedItemNum="2" NeedItemID_1="850000006" NeedItemType_1="1" NeedItemVlaue_1="3" NeedItemID_2="850001007" NeedItemType_2="1" NeedItemValue_2="1" NeedItemID_3="0" NeedItemType_3="0" NeedItemValue_3="0" NeedMoney="3000" Hide="0" NeedItemTyp_3e="0"/>
	<CreateItem Num="17" Name="司思骯腌" GetItemID="286000043" GetItemType="0" GetItemValue="7" GetPer="1000000" NeedItemNum="2" NeedItemID_1="850000006" NeedItemType_1="1" NeedItemVlaue_1="3" NeedItemID_2="850001004" NeedItemType_2="1" NeedItemValue_2="1" NeedItemID_3="0" NeedItemType_3="0" NeedItemValue_3="0" NeedMoney="3000" Hide="0"/>
	<CreateItem Num="18" Name="司思骯腌" GetItemID="286000044" GetItemType="0" GetItemValue="7" GetPer="1000000" NeedItemNum="2" NeedItemID_1="850000006" NeedItemType_1="1" NeedItemVlaue_1="3" NeedItemID_2="850001006" NeedItemType_2="1" NeedItemValue_2="1" NeedItemID_3="0" NeedItemType_3="0" NeedItemValue_3="0" NeedMoney="3000" Hide="0"/>
	<CreateItem Num="19" Name="司思骯腌" GetItemID="286000045" GetItemType="0" GetItemValue="7" GetPer="1000000" NeedItemNum="2" NeedItemID_1="850000006" NeedItemType_1="1" NeedItemVlaue_1="3" NeedItemID_2="850001005" NeedItemType_2="1" NeedItemValue_2="1" NeedItemID_3="0" NeedItemType_3="0" NeedItemValue_3="0" NeedMoney="3000" Hide="0"/>
	<CreateItem Num="20" Name="司思骯腌" GetItemID="286000048" GetItemType="0" GetItemValue="7" GetPer="1000000" NeedItemNum="2" NeedItemID_1="850000005" NeedItemType_1="1" NeedItemVlaue_1="5" NeedItemID_2="850000008" NeedItemType_2="1" NeedItemValue_2="5" NeedItemID_3="0" NeedItemType_3="0" NeedItemValue_3="0" NeedMoney="3000" Hide="0"/>
	<CreateItem Num="21" Name="司思骯腌" GetItemID="286000049" GetItemType="0" GetItemValue="7" GetPer="1000000" NeedItemNum="2" NeedItemID_1="850000005" NeedItemType_1="1" NeedItemVlaue_1="5" NeedItemID_2="850000008" NeedItemType_2="1" NeedItemValue_2="3" NeedItemID_3="0" NeedItemType_3="0" NeedItemValue_3="0" NeedMoney="3000" Hide="0"/>
	<CreateItem Num="22" Name="司思骯腌" GetItemID="286000050" GetItemType="0" GetItemValue="7" GetPer="1000000" NeedItemNum="2" NeedItemID_1="850000005" NeedItemType_1="1" NeedItemVlaue_1="5" NeedItemID_2="850000008" NeedItemType_2="1" NeedItemValue_2="3" NeedItemID_3="0" NeedItemType_3="0" NeedItemValue_3="0" NeedMoney="3000" Hide="0"/>
	<CreateItem Num="23" Name="556司思骯腌" GetItemID="286000051" GetItemType="0" GetItemValue="7" GetPer="1000000" NeedItemNum="2" NeedItemID_1="850000005" NeedItemType_1="1" NeedItemVlaue_1="5" NeedItemID_2="850000008" NeedItemType_2="1" NeedItemValue_2="3" NeedItemID_3="0" NeedItemType_3="0" NeedItemValue_3="0" NeedMoney="3000" Hide="0"/>
	<CreateItem Num="24" Name="司思骯腌" GetItemID="286000052" GetItemType="0" GetItemValue="7" GetPer="1000000" NeedItemNum="2" NeedItemID_1="850000005" NeedItemType_1="1" NeedItemVlaue_1="5" NeedItemID_2="850000008" NeedItemType_2="1" NeedItemValue_2="3" NeedItemID_3="0" NeedItemType_3="0" NeedItemValue_3="0" NeedMoney="3000" Hide="0"/>
	<CreateItem Num="25" Name="I Love You" GetItemID="286000056" GetItemType="0" GetItemValue="7" GetPer="1000000" NeedItemNum="3" NeedItemID_1="850000000" NeedItemType_1="1" NeedItemVlaue_1="3" NeedItemID_2="850000001" NeedItemType_2="1" NeedItemValue_2="3" NeedItemID_3="850000002" NeedItemType_3="1" NeedItemValue_3="3" NeedMoney="2000" Hide="0"/>
	<CreateItem Num="26" Name="司思骯腌" GetItemID="286000060" GetItemType="0" GetItemValue="7" GetPer="1000000" NeedItemNum="2" NeedItemID_1="850000000" NeedItemType_1="1" NeedItemVlaue_1="3" NeedItemID_2="850000001" NeedItemType_2="1" NeedItemValue_2="3" NeedItemID_3="0" NeedItemType_3="0" NeedItemValue_3="0" NeedMoney="2000" Hide="0"/>
	<CreateItem Num="27" Name="司思骯腌" GetItemID="267000029" GetItemType="0" GetItemValue="7" GetPer="1000000" NeedItemNum="3" NeedItemID_1="850000002" NeedItemType_1="1" NeedItemVlaue_1="1" NeedItemID_2="850000004" NeedItemType_2="1" NeedItemValue_2="5" NeedItemID_3="850001004" NeedItemType_3="1" NeedItemValue_3="3" NeedMoney="3000" Hide="0"/>
	<CreateItem Num="28" Name="司思骯腌" GetItemID="267000030" GetItemType="0" GetItemValue="7" GetPer="1000000" NeedItemNum="3" NeedItemID_1="850000002" NeedItemType_1="1" NeedItemVlaue_1="2" NeedItemID_2="850000005" NeedItemType_2="1" NeedItemValue_2="5" NeedItemID_3="850001005" NeedItemType_3="1" NeedItemValue_3="3" NeedMoney="3000" Hide="0"/>
	<CreateItem Num="29" Name="司思骯腌" GetItemID="267000031" GetItemType="0" GetItemValue="7" GetPer="1000000" NeedItemNum="3" NeedItemID_1="850000002" NeedItemType_1="1" NeedItemVlaue_1="3" NeedItemID_2="850000006" NeedItemType_2="1" NeedItemValue_2="5" NeedItemID_3="850001007" NeedItemType_3="1" NeedItemValue_3="3" NeedMoney="3000" Hide="0"/>
	<CreateItem Num="30" Name="司思骯腌" GetItemID="267000032" GetItemType="0" GetItemValue="7" GetPer="1000000" NeedItemNum="3" NeedItemID_1="850000002" NeedItemType_1="1" NeedItemVlaue_1="4" NeedItemID_2="850000007" NeedItemType_2="1" NeedItemValue_2="5" NeedItemID_3="850001006" NeedItemType_3="1" NeedItemValue_3="3" NeedMoney="3000" Hide="0"/>
	<CreateItem Num="31" Name="司思骯腌" GetItemID="267000033" GetItemType="0" GetItemValue="7" GetPer="1000000" NeedItemNum="3" NeedItemID_1="850000002" NeedItemType_1="1" NeedItemVlaue_1="5" NeedItemID_2="850000008" NeedItemType_2="1" NeedItemValue_2="5" NeedItemID_3="850001003" NeedItemType_3="1" NeedItemValue_3="3" NeedMoney="3000" Hide="0"/>
	<CreateItem Num="32" Name="司思骯腌" GetItemID="267000034" GetItemType="0" GetItemValue="7" GetPer="1000000" NeedItemNum="3" NeedItemID_1="850000001" NeedItemType_1="1" NeedItemVlaue_1="1" NeedItemID_2="850000004" NeedItemType_2="1" NeedItemValue_2="5" NeedItemID_3="850001004" NeedItemType_3="1" NeedItemValue_3="2" NeedMoney="2000" Hide="0"/>
	<CreateItem Num="33" Name="司思骯腌" GetItemID="267000035" GetItemType="0" GetItemValue="7" GetPer="1000000" NeedItemNum="3" NeedItemID_1="850000001" NeedItemType_1="1" NeedItemVlaue_1="2" NeedItemID_2="850000005" NeedItemType_2="1" NeedItemValue_2="5" NeedItemID_3="850001005" NeedItemType_3="1" NeedItemValue_3="2" NeedMoney="2000" Hide="0"/>
	<CreateItem Num="34" Name="司思骯腌" GetItemID="267000036" GetItemType="0" GetItemValue="7" GetPer="1000000" NeedItemNum="3" NeedItemID_1="850000001" NeedItemType_1="1" NeedItemVlaue_1="3" NeedItemID_2="850000006" NeedItemType_2="1" NeedItemValue_2="5" NeedItemID_3="850001007" NeedItemType_3="1" NeedItemValue_3="2" NeedMoney="2000" Hide="0"/>
	<CreateItem Num="35" Name="司思骯腌" GetItemID="267000037" GetItemType="0" GetItemValue="7" GetPer="1000000" NeedItemNum="3" NeedItemID_1="850000001" NeedItemType_1="1" NeedItemVlaue_1="4" NeedItemID_2="850000007" NeedItemType_2="1" NeedItemValue_2="5" NeedItemID_3="850001006" NeedItemType_3="1" NeedItemValue_3="2" NeedMoney="2000" Hide="0"/>
	<CreateItem Num="36" Name="司思骯腌" GetItemID="267000038" GetItemType="0" GetItemValue="7" GetPer="1000000" NeedItemNum="3" NeedItemID_1="850000001" NeedItemType_1="1" NeedItemVlaue_1="5" NeedItemID_2="850000008" NeedItemType_2="1" NeedItemValue_2="5" NeedItemID_3="850001003" NeedItemType_3="1" NeedItemValue_3="2" NeedMoney="2000" Hide="0"/>
	<CreateItem Num="37" Name="司思骯腌" GetItemID="267000039" GetItemType="0" GetItemValue="7" GetPer="1000000" NeedItemNum="3" NeedItemID_1="850000000" NeedItemType_1="1" NeedItemVlaue_1="1" NeedItemID_2="850000004" NeedItemType_2="1" NeedItemValue_2="5" NeedItemID_3="850001004" NeedItemType_3="1" NeedItemValue_3="1" NeedMoney="1000" Hide="0"/>
	<CreateItem Num="38" Name="司思骯腌" GetItemID="267000040" GetItemType="0" GetItemValue="7" GetPer="1000000" NeedItemNum="3" NeedItemID_1="850000000" NeedItemType_1="1" NeedItemVlaue_1="2" NeedItemID_2="850000005" NeedItemType_2="1" NeedItemValue_2="5" NeedItemID_3="850001005" NeedItemType_3="1" NeedItemValue_3="1" NeedMoney="1000" Hide="0"/>
	<CreateItem Num="39" Name="司思骯腌" GetItemID="267000041" GetItemType="0" GetItemValue="7" GetPer="1000000" NeedItemNum="3" NeedItemID_1="850000000" NeedItemType_1="1" NeedItemVlaue_1="3" NeedItemID_2="850000006" NeedItemType_2="1" NeedItemValue_2="5" NeedItemID_3="850001007" NeedItemType_3="1" NeedItemValue_3="1" NeedMoney="1000" Hide="0"/>
	<CreateItem Num="40" Name="司思骯腌" GetItemID="267000042" GetItemType="0" GetItemValue="7" GetPer="1000000" NeedItemNum="3" NeedItemID_1="850000000" NeedItemType_1="1" NeedItemVlaue_1="4" NeedItemID_2="850000007" NeedItemType_2="1" NeedItemValue_2="5" NeedItemID_3="850001006" NeedItemType_3="1" NeedItemValue_3="1" NeedMoney="1000" Hide="0"/>
	<CreateItem Num="41" Name="司思骯腌" GetItemID="267000043" GetItemType="0" GetItemValue="7" GetPer="1000000" NeedItemNum="3" NeedItemID_1="850000000" NeedItemType_1="1" NeedItemVlaue_1="5" NeedItemID_2="850000008" NeedItemType_2="1" NeedItemValue_2="5" NeedItemID_3="850001003" NeedItemType_3="1" NeedItemValue_3="1" NeedMoney="1000" Hide="0"/>
	<CreateItem Num="42" Name="司思骯腌" GetItemID="282000082" GetItemType="0" GetItemValue="7" GetPer="1000000" NeedItemNum="2" NeedItemID_1="850000008" NeedItemType_1="1" NeedItemVlaue_1="5" NeedItemID_2="850001003" NeedItemType_2="1" NeedItemValue_2="2" NeedItemID_3="0" NeedItemType_3="0" NeedItemValue_3="0" NeedMoney="1000" Hide="0"/>
	<CreateItem Num="43" Name="司思骯腌" GetItemID="282000083" GetItemType="0" GetItemValue="7" GetPer="1000000" NeedItemNum="2" NeedItemID_1="850000007" NeedItemType_1="1" NeedItemVlaue_1="5" NeedItemID_2="850001006" NeedItemType_2="1" NeedItemValue_2="2" NeedItemID_3="0" NeedItemType_3="0" NeedItemValue_3="0" NeedMoney="1000" Hide="0"/>
	<CreateItem Num="44" Name="司思骯腌" GetItemID="282000084" GetItemType="0" GetItemValue="7" GetPer="1000000" NeedItemNum="2" NeedItemID_1="850000006" NeedItemType_1="1" NeedItemVlaue_1="5" NeedItemID_2="850001007" NeedItemType_2="1" NeedItemValue_2="2" NeedItemID_3="0" NeedItemType_3="0" NeedItemValue_3="0" NeedMoney="1000" Hide="0"/>
	<CreateItem Num="45" Name="司思骯腌" GetItemID="282000085" GetItemType="0" GetItemValue="7" GetPer="1000000" NeedItemNum="2" NeedItemID_1="850000005" NeedItemType_1="1" NeedItemVlaue_1="5" NeedItemID_2="850001005" NeedItemType_2="1" NeedItemValue_2="2" NeedItemID_3="0" NeedItemType_3="0" NeedItemValue_3="0" NeedMoney="1000" Hide="0"/>
	<CreateItem Num="46" Name="司思骯腌" GetItemID="282000098" GetItemType="0" GetItemValue="7" GetPer="1000000" NeedItemNum="2" NeedItemID_1="850000005" NeedItemType_1="1" NeedItemVlaue_1="5" NeedItemID_2="850001003" NeedItemType_2="1" NeedItemValue_2="4" NeedItemID_3="0" NeedItemType_3="0" NeedItemValue_3="0" NeedMoney="2000" Hide="0"/>
	<CreateItem Num="47" Name="司思骯腌" GetItemID="282000099" GetItemType="0" GetItemValue="7" GetPer="1000000" NeedItemNum="2" NeedItemID_1="850000006" NeedItemType_1="1" NeedItemVlaue_1="5" NeedItemID_2="850001006" NeedItemType_2="1" NeedItemValue_2="4" NeedItemID_3="0" NeedItemType_3="0" NeedItemValue_3="0" NeedMoney="2000" Hide="0"/>
	<CreateItem Num="48" Name="司思骯腌" GetItemID="282000100" GetItemType="0" GetItemValue="7" GetPer="1000000" NeedItemNum="2" NeedItemID_1="850000007" NeedItemType_1="1" NeedItemVlaue_1="5" NeedItemID_2="850001007" NeedItemType_2="1" NeedItemValue_2="4" NeedItemID_3="0" NeedItemType_3="0" NeedItemValue_3="0" NeedMoney="2000" Hide="0"/>
	<CreateItem Num="49" Name="司思骯腌" GetItemID="282000101" GetItemType="0" GetItemValue="7" GetPer="1000000" NeedItemNum="2" NeedItemID_1="850000008" NeedItemType_1="1" NeedItemVlaue_1="5" NeedItemID_2="850001005" NeedItemType_2="1" NeedItemValue_2="4" NeedItemID_3="0" NeedItemType_3="0" NeedItemValue_3="0" NeedMoney="2000" Hide="0"/>
	<CreateItem Num="50" Name="司思骯腌" GetItemID="287000116" GetItemType="0" GetItemValue="7" GetPer="1000000" NeedItemNum="3" NeedItemID_1="850000002" NeedItemType_1="1" NeedItemVlaue_1="1" NeedItemID_2="850000004" NeedItemType_2="1" NeedItemValue_2="5" NeedItemID_3="850001004" NeedItemType_3="0" NeedItemValue_3="0" NeedMoney="3000" Hide="0"/>
	<CreateItem Num="51" Name="司思骯腌" GetItemID="287000117" GetItemType="0" GetItemValue="7" GetPer="1000000" NeedItemNum="3" NeedItemID_1="850000002" NeedItemType_1="1" NeedItemVlaue_1="2" NeedItemID_2="850000005" NeedItemType_2="1" NeedItemValue_2="5" NeedItemID_3="850001005" NeedItemType_3="0" NeedItemValue_3="0" NeedMoney="3000" Hide="0"/>
	<CreateItem Num="52" Name="司思骯腌" GetItemID="287000118" GetItemType="0" GetItemValue="7" GetPer="1000000" NeedItemNum="3" NeedItemID_1="850000002" NeedItemType_1="1" NeedItemVlaue_1="3" NeedItemID_2="850000006" NeedItemType_2="1" NeedItemValue_2="5" NeedItemID_3="850001007" NeedItemType_3="0" NeedItemValue_3="0" NeedMoney="3000" Hide="0"/>
	<CreateItem Num="53" Name="司思骯腌" GetItemID="287000119" GetItemType="0" GetItemValue="7" GetPer="1000000" NeedItemNum="3" NeedItemID_1="850000002" NeedItemType_1="1" NeedItemVlaue_1="4" NeedItemID_2="850000007" NeedItemType_2="1" NeedItemValue_2="5" NeedItemID_3="850001006" NeedItemType_3="0" NeedItemValue_3="0" NeedMoney="3000" Hide="0"/>
	<CreateItem Num="54" Name="司思骯腌" GetItemID="287000120" GetItemType="0" GetItemValue="7" GetPer="1000000" NeedItemNum="3" NeedItemID_1="850000002" NeedItemType_1="1" NeedItemVlaue_1="5" NeedItemID_2="850000008" NeedItemType_2="1" NeedItemValue_2="5" NeedItemID_3="850001003" NeedItemType_3="0" NeedItemValue_3="0" NeedMoney="3000" Hide="0"/>
	<CreateItem Num="55" Name="司思骯腌" GetItemID="287000121" GetItemType="0" GetItemValue="7" GetPer="1000000" NeedItemNum="3" NeedItemID_1="850000001" NeedItemType_1="1" NeedItemVlaue_1="1" NeedItemID_2="850000004" NeedItemType_2="1" NeedItemValue_2="5" NeedItemID_3="850001004" NeedItemType_3="0" NeedItemValue_3="0" NeedMoney="2000" Hide="0"/>
	<CreateItem Num="56" Name="司思骯腌" GetItemID="287000122" GetItemType="0" GetItemValue="7" GetPer="1000000" NeedItemNum="3" NeedItemID_1="850000001" NeedItemType_1="1" NeedItemVlaue_1="2" NeedItemID_2="850000005" NeedItemType_2="1" NeedItemValue_2="5" NeedItemID_3="850001005" NeedItemType_3="0" NeedItemValue_3="0" NeedMoney="2000" Hide="0"/>
	<CreateItem Num="57" Name="司思骯腌" GetItemID="287000123" GetItemType="0" GetItemValue="7" GetPer="1000000" NeedItemNum="3" NeedItemID_1="850000001" NeedItemType_1="1" NeedItemVlaue_1="3" NeedItemID_2="850000006" NeedItemType_2="1" NeedItemValue_2="5" NeedItemID_3="850001007" NeedItemType_3="0" NeedItemValue_3="0" NeedMoney="2000" Hide="0"/>
	<CreateItem Num="58" Name="司思骯腌" GetItemID="287000124" GetItemType="0" GetItemValue="7" GetPer="1000000" NeedItemNum="3" NeedItemID_1="850000001" NeedItemType_1="1" NeedItemVlaue_1="4" NeedItemID_2="850000007" NeedItemType_2="1" NeedItemValue_2="5" NeedItemID_3="850001006" NeedItemType_3="0" NeedItemValue_3="0" NeedMoney="2000" Hide="0"/>
	<CreateItem Num="59" Name="司思骯腌" GetItemID="287000125" GetItemType="0" GetItemValue="7" GetPer="1000000" NeedItemNum="3" NeedItemID_1="850000001" NeedItemType_1="1" NeedItemVlaue_1="5" NeedItemID_2="850000008" NeedItemType_2="1" NeedItemValue_2="5" NeedItemID_3="850001003" NeedItemType_3="0" NeedItemValue_3="0" NeedMoney="2000" Hide="0"/>
	<CreateItem Num="60" Name="司思骯腌" GetItemID="287000126" GetItemType="0" GetItemValue="7" GetPer="1000000" NeedItemNum="3" NeedItemID_1="850000000" NeedItemType_1="1" NeedItemVlaue_1="1" NeedItemID_2="850000004" NeedItemType_2="1" NeedItemValue_2="5" NeedItemID_3="850001004" NeedItemType_3="0" NeedItemValue_3="0" NeedMoney="1000" Hide="0"/>
	<CreateItem Num="61" Name="司思骯腌" GetItemID="287000127" GetItemType="0" GetItemValue="7" GetPer="1000000" NeedItemNum="3" NeedItemID_1="850000000" NeedItemType_1="1" NeedItemVlaue_1="2" NeedItemID_2="850000005" NeedItemType_2="1" NeedItemValue_2="5" NeedItemID_3="850001005" NeedItemType_3="0" NeedItemValue_3="0" NeedMoney="1000" Hide="0"/>
	<CreateItem Num="62" Name="司思骯腌" GetItemID="287000128" GetItemType="0" GetItemValue="7" GetPer="1000000" NeedItemNum="3" NeedItemID_1="850000000" NeedItemType_1="1" NeedItemVlaue_1="3" NeedItemID_2="850000006" NeedItemType_2="1" NeedItemValue_2="5" NeedItemID_3="850001007" NeedItemType_3="0" NeedItemValue_3="0" NeedMoney="1000" Hide="0"/>
	<CreateItem Num="63" Name="司思骯腌" GetItemID="287000129" GetItemType="0" GetItemValue="7" GetPer="1000000" NeedItemNum="3" NeedItemID_1="850000000" NeedItemType_1="1" NeedItemVlaue_1="4" NeedItemID_2="850000007" NeedItemType_2="1" NeedItemValue_2="5" NeedItemID_3="850001006" NeedItemType_3="0" NeedItemValue_3="0" NeedMoney="1000" Hide="0"/>
	<CreateItem Num="64" Name="司思骯腌" GetItemID="287000130" GetItemType="0" GetItemValue="7" GetPer="1000000" NeedItemNum="3" NeedItemID_1="850000000" NeedItemType_1="1" NeedItemVlaue_1="5" NeedItemID_2="850000008" NeedItemType_2="1" NeedItemValue_2="5" NeedItemID_3="850001003" NeedItemType_3="0" NeedItemValue_3="0" NeedMoney="1000" Hide="0"/>
	<CreateItem Num="65" Name="司思骯腌" GetItemID="661000000" GetItemType="1" GetItemValue="1" GetPer="7" NeedItemNum="3" NeedItemID_1="850000006" NeedItemType_1="1" NeedItemVlaue_1="7" NeedItemID_2="850001001" NeedItemType_2="1" NeedItemValue_2="5" NeedItemID_3="850001002" NeedItemType_3="1" NeedItemValue_3="3" NeedMoney="15000" Hide="0"/>
	<CreateItem Num="66" Name="司思骯腌" GetItemID="671000000" GetItemType="1" GetItemValue="1" GetPer="30" NeedItemNum="3" NeedItemID_1="850000000" NeedItemType_1="1" NeedItemVlaue_1="3" NeedItemID_2="850001001" NeedItemType_2="1" NeedItemValue_2="3" NeedItemID_3="850001002" NeedItemType_3="1" NeedItemValue_3="5" NeedMoney="5000" Hide="0"/>
	<CreateItem Num="67" Name="司思骯腌" GetItemID="601000000" GetItemType="1" GetItemValue="1" GetPer="10" NeedItemNum="3" NeedItemID_1="850000004" NeedItemType_1="1" NeedItemVlaue_1="5" NeedItemID_2="850001001" NeedItemType_2="1" NeedItemValue_2="0" NeedItemID_3="850001002" NeedItemType_3="1" NeedItemValue_3="0" NeedMoney="10000" Hide="0"/>
	<CreateItem Num="68" Name="司思骯腌" GetItemID="611000000" GetItemType="1" GetItemValue="1" GetPer="10" NeedItemNum="3" NeedItemID_1="850000002" NeedItemType_1="1" NeedItemVlaue_1="5" NeedItemID_2="850001001" NeedItemType_2="1" NeedItemValue_2="0" NeedItemID_3="850001002" NeedItemType_3="1" NeedItemValue_3="0" NeedMoney="10000" Hide="0"/>
	<CreateItem Num="69" Name="司思骯腌" GetItemID="621000000" GetItemType="1" GetItemValue="1" GetPer="10" NeedItemNum="3" NeedItemID_1="850000005" NeedItemType_1="1" NeedItemVlaue_1="5" NeedItemID_2="850001001" NeedItemType_2="1" NeedItemValue_2="0" NeedItemID_3="850001002" NeedItemType_3="1" NeedItemValue_3="0" NeedMoney="10000" Hide="0"/>
	<CreateItem Num="70" Name="司思骯腌" GetItemID="651000000" GetItemType="1" GetItemValue="1" GetPer="10" NeedItemNum="3" NeedItemID_1="850000003" NeedItemType_1="1" NeedItemVlaue_1="5" NeedItemID_2="850001001" NeedItemType_2="1" NeedItemValue_2="0" NeedItemID_3="850001002" NeedItemType_3="1" NeedItemValue_3="0" NeedMoney="10000" Hide="0"/>
	<CreateItem Num="71" Name="司思骯腌" GetItemID="631000000" GetItemType="1" GetItemValue="1" GetPer="10" NeedItemNum="3" NeedItemID_1="850000006" NeedItemType_1="1" NeedItemVlaue_1="5" NeedItemID_2="850001001" NeedItemType_2="1" NeedItemValue_2="0" NeedItemID_3="850001002" NeedItemType_3="1" NeedItemValue_3="0" NeedMoney="10000" Hide="0"/>
	<CreateItem Num="72" Name="司思骯腌" GetItemID="662000001" GetItemType="1" GetItemValue="1" GetPer="25" NeedItemNum="3" NeedItemID_1="850000004" NeedItemType_1="1" NeedItemVlaue_1="0" NeedItemID_2="850001001" NeedItemType_2="1" NeedItemValue_2="0" NeedItemID_3="850001006" NeedItemType_3="1" NeedItemValue_3="0" NeedMoney="8000" Hide="0"/>
	<CreateItem Num="73" Name="司思骯腌" GetItemID="662000002" GetItemType="1" GetItemValue="1" GetPer="20" NeedItemNum="3" NeedItemID_1="850000005" NeedItemType_1="1" NeedItemVlaue_1="0" NeedItemID_2="850001001" NeedItemType_2="1" NeedItemValue_2="0" NeedItemID_3="850001005" NeedItemType_3="1" NeedItemValue_3="0" NeedMoney="10000" Hide="0"/>
	<CreateItem Num="74" Name="司思骯腌" GetItemID="662000003" GetItemType="1" GetItemValue="1" GetPer="10" NeedItemNum="3" NeedItemID_1="850000006" NeedItemType_1="1" NeedItemVlaue_1="0" NeedItemID_2="850001001" NeedItemType_2="1" NeedItemValue_2="0" NeedItemID_3="850001007" NeedItemType_3="1" NeedItemValue_3="0" NeedMoney="12000" Hide="0"/>
	<CreateItem Num="75" Name="司思骯腌" GetItemID="662000004" GetItemType="1" GetItemValue="1" GetPer="7" NeedItemNum="3" NeedItemID_1="850000007" NeedItemType_1="1" NeedItemVlaue_1="7" NeedItemID_2="850001001" NeedItemType_2="1" NeedItemValue_2="5" NeedItemID_3="850001004" NeedItemType_3="1" NeedItemValue_3="3" NeedMoney="15000" Hide="0"/>
	<CreateItem Num="76" Name="司思骯腌" GetItemID="662000005" GetItemType="1" GetItemValue="1" GetPer="5" NeedItemNum="3" NeedItemID_1="850000008" NeedItemType_1="1" NeedItemVlaue_1="10" NeedItemID_2="850001001" NeedItemType_2="1" NeedItemValue_2="7" NeedItemID_3="850001003" NeedItemType_3="1" NeedItemValue_3="5" NeedMoney="20000" Hide="0"/>
	<CreateItem Num="77" Name="司思骯腌" GetItemID="287000081" GetItemType="0" GetItemValue="30" GetPer="1000000" NeedItemNum="3" NeedItemID_1="850000001" NeedItemType_1="1" NeedItemVlaue_1="5" NeedItemID_2="850001002" NeedItemType_2="1" NeedItemValue_2="5" NeedItemID_3="850001006" NeedItemType_3="0" NeedItemValue_3="3" NeedMoney="2000" Hide="0"/>
	<CreateItem Num="78" Name="司思骯腌" GetItemID="287000072" GetItemType="0" GetItemValue="30" GetPer="1000000" NeedItemNum="3" NeedItemID_1="850000001" NeedItemType_1="1" NeedItemVlaue_1="5" NeedItemID_2="850001002" NeedItemType_2="1" NeedItemValue_2="5" NeedItemID_3="850001003" NeedItemType_3="0" NeedItemValue_3="3" NeedMoney="2000" Hide="0"/>
	<CreateItem Num="79" Name="司思骯腌" GetItemID="287000073" GetItemType="0" GetItemValue="30" GetPer="1000000" NeedItemNum="3" NeedItemID_1="850000001" NeedItemType_1="1" NeedItemVlaue_1="5" NeedItemID_2="850001002" NeedItemType_2="1" NeedItemValue_2="5" NeedItemID_3="850001007" NeedItemType_3="0" NeedItemValue_3="3" NeedMoney="2000" Hide="0"/>
	<CreateItem Num="80" Name="司思骯腌" GetItemID="287000074" GetItemType="0" GetItemValue="30" GetPer="1000000" NeedItemNum="3" NeedItemID_1="850000001" NeedItemType_1="1" NeedItemVlaue_1="5" NeedItemID_2="850001002" NeedItemType_2="1" NeedItemValue_2="5" NeedItemID_3="850001005" NeedItemType_3="0" NeedItemValue_3="3" NeedMoney="2000" Hide="0"/>
	<CreateItem Num="81" Name="司思骯腌" GetItemID="287000086" GetItemType="0" GetItemValue="30" GetPer="1000000" NeedItemNum="3" NeedItemID_1="850000001" NeedItemType_1="1" NeedItemVlaue_1="5" NeedItemID_2="850001004" NeedItemType_2="1" NeedItemValue_2="3" NeedItemID_3="850001003" NeedItemType_3="0" NeedItemValue_3="3" NeedMoney="2000" Hide="0"/>
	<CreateItem Num="82" Name="司思骯腌" GetItemID="287000087" GetItemType="0" GetItemValue="30" GetPer="1000000" NeedItemNum="3" NeedItemID_1="850000001" NeedItemType_1="1" NeedItemVlaue_1="5" NeedItemID_2="850001007" NeedItemType_2="1" NeedItemValue_2="3" NeedItemID_3="850001006" NeedItemType_3="0" NeedItemValue_3="3" NeedMoney="2000" Hide="0"/>
	<CreateItem Num="83" Name="司思骯腌" GetItemID="287000088" GetItemType="0" GetItemValue="30" GetPer="1000000" NeedItemNum="3" NeedItemID_1="850000001" NeedItemType_1="1" NeedItemVlaue_1="5" NeedItemID_2="850001005" NeedItemType_2="1" NeedItemValue_2="3" NeedItemID_3="850001003" NeedItemType_3="0" NeedItemValue_3="3" NeedMoney="2000" Hide="0"/>
	<CreateItem Num="84" Name="司思骯腌" GetItemID="287000094" GetItemType="0" GetItemValue="7" GetPer="100" NeedItemNum="3" NeedItemID_1="850000008" NeedItemType_1="1" NeedItemVlaue_1="10" NeedItemID_2="850001001" NeedItemType_2="1" NeedItemValue_2="10" NeedItemID_3="850001002" NeedItemType_3="1" NeedItemValue_3="5" NeedMoney="3000" Hide="0"/>
</CreateItemProperty>