<?xml version="1.0" encoding="ks_c_5601_1987" ?>
<GAMEENTITY>
    <MODEL_RES_LIST COUNT="1">
        <PROPERTYBAG NAME="Viper2_3_doorRight3" FILENAME="Viper2_3_doorRight3.xml" COMMENT="" />
    </MODEL_RES_LIST>
    <ANIM_RES_LIST COUNT="1" VSNAME="Viper2_3_doorRight3.VS">
        <PROPERTYBAG NAME="Viper2_3_doorRight3" FILENAME="Viper2_3_doorRight3.VA" COMMENT="" />
    </ANIM_RES_LIST>
    <SOUND_RES_LIST COUNT="0" />
    <EFFECT_RES_LIST COUNT="0" />
    <PARTICLE_RES_LIST COUNT="0" />
    <EXTENTITY_RES_LIST COUNT="0" />
    <COMMANDS FILENAME="Viper2_3_doorRight3_COMMANDS.XML" />
</GAMEENTITY>
