<?xml version="1.0" encoding="ks_c_5601_1987" ?>
<GAMEENTITY>
    <MODEL_RES_LIST COUNT="1">
        <PROPERTYBAG NAME="GIRO_GRANDE" FILENAME="Giro_Aniob_Grenade.xml" COMMENT="" />
    </MODEL_RES_LIST>
    <ANIM_RES_LIST COUNT="1" VSNAME="Giro_Obj_Grenade.VS">
        <PROPERTYBAG NAME="GIRO_GRANDE" FILENAME="Giro_Obj_Grenade.VA" COMMENT="" />
    </ANIM_RES_LIST>
    <SOUND_RES_LIST COUNT="0" />
    <EFFECT_RES_LIST COUNT="0" />
    <PARTICLE_RES_LIST COUNT="0" />
    <EXTENTITY_RES_LIST COUNT="0" />
    <COMMANDS FILENAME="Giro_Grenade_COMMANDS.XML" />
</GAMEENTITY>
