<?xml version="1.0" encoding="ks_c_5601_1987" ?>
<CHARACTER>
    <COMMAND_LIST>
        <COMMAND NAME="SPE_04_1" LOOP="0" TOTALTIME="1.330000">
            <ACTIONEVENT CLASSNAME="CActionEvent_ActionAni" EVENTNAME="Joru_Comb_SPE_04" TYPENAME="ActionAnimation" ANIMATIONNAME="Joru_Comb_SPE_04" FADEIN="0.100000" FADEOUT="0.100000" WEIGHT="1.000000" EVENTTIME="0.000000" EVENTENDTIME="0.000000" />
            <ACTIONEVENT CLASSNAME="CActionEvent_ExtEntity" EVENTNAME="Joru_Sword_SPE_04" TYPENAME="ExtEntity" ENTITYNAME="Joru_Sword_SPE_04" POSX="0.000000" POSY="0.000000" POSZ="0.000000" ROTX="0.000000" ROTY="0.000000" ROTZ="0.000000" BONENAME="" ANIMATIONNAME="JORU_SWORD_SPE_04" REFCREPOS="0" EVENTTIME="0.000000" EVENTENDTIME="1.190000" />
            <ACTIONEVENT CLASSNAME="CActionEvent_LoopAni" EVENTNAME="Joru_Combat_Wait" TYPENAME="LoopAnimation" ANIMATIONNAME="Joru_Combat_Wait" WEIGHT="1.000000" DELAY="0.100000" EVENTTIME="0.000000" EVENTENDTIME="0.000000" />
            <ACTIONEVENT CLASSNAME="CActionEvent_Particle" EVENTNAME="Joru_SPE_P00" TYPENAME="Particle" PARTICLENAME="Joru_SPE_P00" OFFSETX="0.000000" OFFSETY="0.000000" OFFSETZ="0.000000" USEBONE="1" BONENAME="Bip01" TERMINATE="0" EVENTTIME="0.000000" EVENTENDTIME="0.000000" />
        </COMMAND>
    </COMMAND_LIST>
</CHARACTER>
